memx_sdk/__init__.py
memx_sdk/client.py
memx_sdk/test_client.py
memx_sdk-0.1.2.dist-info/METADATA
memx_sdk-0.1.2.dist-info/WHEEL
memx_sdk-0.1.2.dist-info/licenses/LICENSE
memx_sdk-0.1.2.dist-info/RECORD
