Metadata-Version: 2.4
Name: memx-sdk
Version: 0.1.2
Summary: Python client for memX shared memory platform
Project-URL: Homepage, https://github.com/MehulG/memx
Project-URL: Repository, https://github.com/MehulG/memx
Project-URL: Documentation, https://github.com/MehulG/memx#readme
Author-email: Mehul <memx.founders@gmail.com>
License: MIT
License-File: LICENSE
Requires-Python: >=3.8
Requires-Dist: hatchling<2.0.0,>=1.27.0
Requires-Dist: httpx>=0.24.0
Requires-Dist: websockets
